{
  "color": {
    "blue": "#2776EA",
    "blue-soft": "#6AADF5",
    "navy": "#1255B2",
    "cyan": "#1FAFC4",
    "sage": "#5E7E7C",
    "paper": "#FFFFFF",
    "cream": "#EAEFF6",
    "sand": "#DBE2EC",
    "ink": "#15181F",
    "btn": "#121419",
    "gray-60": "#666666",
    "gray-40": "#999999",
    "paper-tint": "var(--cream)",
    "snow": "var(--cream)",
    "stone": "var(--sand)",
    "rule": "rgba(21, 24, 31, 0.12)",
    "rule-strong": "rgba(21, 24, 31, 0.22)"
  },
  "layout": {
    "maxw": "1240px",
    "content-max": "1240px",
    "gutter": "32px",
    "nav-h": "68px"
  },
  "radius": {
    "sm": "10px",
    "md": "14px",
    "lg": "22px",
    "card": "22px",
    "pill": "999px"
  },
  "font": {
    "display": "'Geist', sans-serif",
    "sans": "'Geist', ui-sans-serif, system-ui, sans-serif",
    "mono": "'Geist Mono', ui-monospace, monospace",
    "italic": "'Geist', sans-serif"
  }
}
